eopsin/__init__.py
eopsin/exchange/__init__.py
eopsin/exchange/binance.py
eopsin/exchange/emulator.py
eopsin/exchange/exchange.py
eopsin/model/__init__.py
eopsin/model/_sqlbase.py
eopsin/model/candle.py
eopsin/model/exchange.py
eopsin/model/order.py
eopsin/model/pair.py
eopsin/model/timestamp.py
eopsin/service/__init__.py
eopsin/service/dbservice.py
eopsin/strategy/__init__.py
eopsin/strategy/strategy.py
eopsin/tests/__init__.py
eopsin/tests/unit/__init__.py
eopsin/tests/unit/binance_test.py
eopsin/tests/unit/dbservice_test.py
eopsin/tests/unit/emulator_test.py
eopsin/tests/unit/events_test.py
eopsin/tests/unit/util_test.py
eopsin/util/__init__.py
eopsin/util/events.py
eopsin/util/roundDatetime.py
eopsin-0.2.0.dist-info/LICENSE
eopsin-0.2.0.dist-info/METADATA
eopsin-0.2.0.dist-info/WHEEL
eopsin-0.2.0.dist-info/top_level.txt
eopsin-0.2.0.dist-info/RECORD
